[
    {
        "id" : 1,
        "ket" : "Mulai di: Al-Fatihah Ayat 1"
    },
    {
        "id" : 2,
        "ket" : "Mulai di: Al-Baqarah Ayat 142"
    },
    {
        "id" : 3,
        "ket" : "Mulai di: Al-Baqarah Ayat 253"
    },
    {
        "id" : 4,
        "ket" : "Mulai di: Al-'Imran Ayat 92"
    },
    {
        "id" : 5,
        "ket" : "Mulai di: Al-Nisa' Ayat 24"
    },
    {
        "id" : 6,
        "ket" : "Mulai di: Al-Nisa' Ayat 148"
    },
    {
        "id" : 7,
        "ket" : "Mulai di: Al-Ma'idah Ayat 83"
    },
    {
        "id" : 8,
        "ket" : "Mulai di: Al-An'nam Ayat 111"
    },
    {
        "id" : 9,
        "ket" : "Mulai di: Al-A'Raf Ayat 88"
    },
    {
        "id" : 10,
        "ket" : "Mulai di: Al-Anfal Ayat 41"
    },
    {
        "id" : 11,
        "ket" : "Mulai di: At-Taubah Ayat 94"
    },
    {
        "id" : 12,
        "ket" : "Mulai di: Hud Ayat 6"
    },
    {
        "id" : 13,
        "ket" : "Mulai di: Yusuf Ayat 53"
    },
    {
        "id" : 14,
        "ket" : "Mulai di: Al-Hijr Ayat 2"
    },
    {
        "id" : 15,
        "ket" : "Mulai di: Al-Isra' Ayat 1"
    },
    {
        "id" : 16,
        "ket" : "Mulai di: Al-Kahf Ayat 75"
    },
    {
        "id" : 17,
        "ket" : "Mulai di: Al-Anbiya Ayat 1"
    },
    {
        "id" : 18,
        "ket" : "Mulai di: Al-Mu'Minun Ayat 1"
    },
    {
        "id" : 19,
        "ket" : "Mulai di: Al-Furqan Ayat 21"
    },
    {
        "id" : 20,
        "ket" : "Mulai di: An-Naml Ayat 60"
    },
    {
        "id" : 21,
        "ket" : "Mulai di: Al-'Ankabut' Ayat 45"
    },
    {
        "id" : 22,
        "ket" : "Mulai di: Al-Ahzab Ayat 31"
    },
    {
        "id" : 23,
        "ket" : "Mulai di: Ya-Sin Ayat 22"
    },
    {
        "id" : 24,
        "ket" : "Mulai di: Az-Zumar Ayat 32"
    },
    {
        "id" : 25,
        "ket" : "Mulai di: Fussilat Ayat 47"
    },
    {
        "id" : 26,
        "ket" : "Mulai di: Al-Ahqaf Ayat 1"
    },
    {
        "id" : 27,
        "ket" : "Mulai di: Az-Zariyat Ayat 31"
    },
    {
        "id" : 28,
        "ket" : "Mulai di: Al-Mujadilah Ayat 1"
    },
    {
        "id" : 29,
        "ket" : "Mulai di: Al-Mulk Ayat 1"
    },
    {
        "id" : 30,
        "ket" : "Mulai di: An-Naba' Ayat 1"
    }
    
]